qenerate/__init__.py
qenerate/cli.py
qenerate/core/__init__.py
qenerate/core/code_command.py
qenerate/core/feature_flag_parser.py
qenerate/core/introspection_command.py
qenerate/core/plugin.py
qenerate/core/preprocessor.py
qenerate/core/unwrapper.py
qenerate/plugins/__init__.py
qenerate/plugins/pydantic_v2/__init__.py
qenerate/plugins/pydantic_v2/mapper.py
qenerate/plugins/pydantic_v2/plugin.py
qenerate/plugins/pydantic_v2/typed_ast.py
qenerate_custom-0.7.1.dist-info/LICENSE
qenerate_custom-0.7.1.dist-info/METADATA
qenerate_custom-0.7.1.dist-info/WHEEL
qenerate_custom-0.7.1.dist-info/entry_points.txt
qenerate_custom-0.7.1.dist-info/RECORD
